libxrk-0.7.0.dist-info/RECORD
libxrk-0.7.0.dist-info/WHEEL
libxrk-0.7.0.dist-info/METADATA
libxrk-0.7.0.dist-info/licenses/LICENSE
libxrk/aim_xrk.cpython-311-darwin.so
libxrk/gps.py
libxrk/aim_xrk.pyx
libxrk/__init__.py
libxrk/aim_xrk.pyi
libxrk/py.typed
libxrk/base.py
libxrk/CLAUDE.md
