Metadata-Version: 2.4
Name: libxrk
Version: 0.7.0
Summary: Library for reading AIM XRK files from AIM automotive data loggers
License-File: LICENSE
Author: Christopher Dewan
Author-email: chris.dewan@m3rlin.net
Requires-Python: >=3.10
Classifier: Development Status :: 4 - Beta
Classifier: Intended Audience :: Developers
Classifier: License :: OSI Approved :: MIT License
Classifier: Programming Language :: Python :: 3
Classifier: Programming Language :: Python :: 3.10
Classifier: Programming Language :: Python :: 3.11
Classifier: Programming Language :: Python :: 3.12
Classifier: Programming Language :: Python :: 3.13
Classifier: Programming Language :: Python :: 3.14
Classifier: Programming Language :: Cython
Classifier: Topic :: Scientific/Engineering
Provides-Extra: dev
Provides-Extra: test
Requires-Dist: cython (>=3.0.0)
Requires-Dist: numpy (>=1.26.0) ; python_version < "3.13"
Requires-Dist: numpy (>=2.1.0) ; python_version == "3.13"
Requires-Dist: numpy (>=2.4.0) ; python_version >= "3.14"
Requires-Dist: parameterized (>=0.9.0) ; extra == "dev"
Requires-Dist: parameterized (>=0.9.0) ; extra == "test"
Requires-Dist: pyarrow (>=18.1.0) ; python_version < "3.14"
Requires-Dist: pyarrow (>=22.0.0) ; python_version >= "3.14"
Requires-Dist: pytest (>=7.0.0) ; extra == "dev"
Requires-Dist: pytest (>=7.0.0) ; extra == "test"
Requires-Dist: setuptools (>=68.0.0) ; extra == "dev"
Project-URL: Homepage, https://github.com/m3rlin45/libxrk
Project-URL: Issues, https://github.com/m3rlin45/libxrk/issues
Project-URL: Repository, https://github.com/m3rlin45/libxrk
